chemax/__init__.py
chemax/computer.py
chemax/molecule.py
chemax/datas/__init__.py
chemax/datas/abundant_nuclide.py
chemax/datas/balance.py
chemax/datas/groups.py
chemax/datas/nuclide.py
chemax-1.0.1.dist-info/LICENSE
chemax-1.0.1.dist-info/METADATA
chemax-1.0.1.dist-info/WHEEL
chemax-1.0.1.dist-info/top_level.txt
chemax-1.0.1.dist-info/RECORD
