Metadata-Version: 2.1
Name: chemax
Version: 1.0.1
Summary: Easily calculate the m.w. and e.m of a molecule
Home-page: https://github.com/HisAtri/chemax
Author: HisAtri
Author-email: ylsymc@outlook.com
Classifier: Programming Language :: Python :: 3
Classifier: License :: OSI Approved :: MIT License
Classifier: Operating System :: OS Independent
License-File: LICENSE
